{
    "argv": 453,
    "bounds": [
        [
            5.848410588726615e-12,
            0.005848410588726615
        ],
        [
            0.05848410588726615,
            0.1169682117745323
        ],
        [
            0.0,
            11.0
        ],
        [
            0.0,
            null
        ],
        [
            0.0,
            null
        ],
        [
            0.0,
            null
        ],
        [
            0.0,
            null
        ],
        [
            0.0,
            null
        ],
        [
            0.0,
            null
        ],
        [
            0.0,
            null
        ],
        [
            0.0,
            null
        ],
        [
            0.0,
            null
        ],
        [
            0.0,
            null
        ],
        [
            0.0,
            null
        ],
        [
            0.0,
            null
        ],
        [
            0.0,
            null
        ],
        [
            0.0,
            null
        ],
        [
            0.0,
            null
        ],
        [
            0.0,
            null
        ],
        [
            0.0,
            null
        ],
        [
            0.0,
            null
        ],
        [
            0.0,
            null
        ],
        [
            0.0,
            null
        ],
        [
            0.0,
            null
        ],
        [
            0.0,
            null
        ],
        [
            0.0,
            null
        ],
        [
            0.0,
            null
        ],
        [
            0.0,
            null
        ]
    ],
    "comp_est": [
        6.250250716568048e-06,
        0.05848410588726615,
        10.903858343332647,
        64.08204265312689,
        62.614702207070316,
        65.3135249717976,
        65.77151134746111,
        62.32862780554563,
        59.21000711948595,
        60.35886966113404,
        62.87067997779107,
        65.6794489813971,
        76.70638600209581,
        64.77219957915358,
        64.5880918070158,
        62.75427207095374,
        75.12247481866906,
        61.55932614601226,
        64.91018726375559,
        64.8421913835288,
        61.29742480206848,
        62.16994778112824,
        62.418617211656546,
        61.04395305513113,
        65.51573038338543,
        76.34679198990324,
        63.25665516508552,
        61.32462682373059
    ],
    "fit_time": 533.4239554405212,
    "init_guess": [
        5.848410588726615e-09,
        0.05848410588726615,
        2.0,
        65.0,
        65.0,
        65.0,
        65.0,
        65.0,
        65.0,
        65.0,
        65.0,
        65.0,
        65.0,
        65.0,
        65.0,
        65.0,
        65.0,
        65.0,
        65.0,
        65.0,
        65.0,
        65.0,
        65.0,
        65.0,
        65.0,
        65.0,
        65.0,
        65.0
    ],
    "model": "Competition Model",
    "model_params": [
        "C_0",
        "N_0",
        "kn",
        "rs"
    ],
    "model_species": [
        "C",
        "N"
    ],
    "obj_fun": 0.09209561620822919,
    "zone_cols": 5,
    "zone_coords": [
        7,
        13
    ],
    "zone_rows": 5
}