{
    "argv": 674,
    "bounds": [
        [
            6.437222058477453e-12,
            0.006437222058477453
        ],
        [
            0.06437222058477453,
            0.12874444116954906
        ],
        [
            0.0,
            11.0
        ],
        [
            0.0,
            null
        ],
        [
            0.0,
            null
        ],
        [
            0.0,
            null
        ],
        [
            0.0,
            null
        ],
        [
            0.0,
            null
        ],
        [
            0.0,
            null
        ],
        [
            0.0,
            null
        ],
        [
            0.0,
            null
        ],
        [
            0.0,
            null
        ],
        [
            0.0,
            null
        ],
        [
            0.0,
            null
        ],
        [
            0.0,
            null
        ],
        [
            0.0,
            null
        ],
        [
            0.0,
            null
        ],
        [
            0.0,
            null
        ],
        [
            0.0,
            null
        ],
        [
            0.0,
            null
        ],
        [
            0.0,
            null
        ],
        [
            0.0,
            null
        ],
        [
            0.0,
            null
        ],
        [
            0.0,
            null
        ],
        [
            0.0,
            null
        ],
        [
            0.0,
            null
        ],
        [
            0.0,
            null
        ],
        [
            0.0,
            null
        ]
    ],
    "comp_est": [
        2.1061604868703414e-07,
        0.07750172093113342,
        3.0168531055905183,
        54.427197764403324,
        56.84272802651807,
        54.61195110143455,
        54.63792471349556,
        54.4616367894763,
        54.234434521169085,
        54.51043826995911,
        54.36760567263339,
        52.91755435690392,
        57.35119087148455,
        57.11128760965422,
        54.61053123263226,
        54.494957858069434,
        56.07529181202535,
        54.21301170611661,
        53.921025138146994,
        56.615987400202236,
        53.94503114153512,
        57.71541103479127,
        54.284441514177445,
        54.52279042651122,
        54.74699502972464,
        54.83434204507674,
        54.63856685290393,
        54.25586542321887
    ],
    "fit_time": 26790.809840917587,
    "init_guess": [
        6.437222058477454e-07,
        0.06437222058477453,
        3.0,
        55.0,
        55.0,
        55.0,
        55.0,
        55.0,
        55.0,
        55.0,
        55.0,
        55.0,
        55.0,
        55.0,
        55.0,
        55.0,
        55.0,
        55.0,
        55.0,
        55.0,
        55.0,
        55.0,
        55.0,
        55.0,
        55.0,
        55.0,
        55.0,
        55.0
    ],
    "model": "Competition Model",
    "model_params": [
        "C_0",
        "N_0",
        "kn",
        "rs"
    ],
    "model_species": [
        "C",
        "N"
    ],
    "obj_fun": 0.4892451760615517,
    "zone_cols": 5,
    "zone_coords": [
        9,
        15
    ],
    "zone_rows": 5
}