{
    "argv": 70,
    "bounds": [
        [
            5.848410588726615e-12,
            0.005848410588726615
        ],
        [
            0.05848410588726615,
            0.1169682117745323
        ],
        [
            0.0,
            11.0
        ],
        [
            0.0,
            null
        ],
        [
            0.0,
            null
        ],
        [
            0.0,
            null
        ],
        [
            0.0,
            null
        ],
        [
            0.0,
            null
        ],
        [
            0.0,
            null
        ],
        [
            0.0,
            null
        ],
        [
            0.0,
            null
        ],
        [
            0.0,
            null
        ],
        [
            0.0,
            null
        ],
        [
            0.0,
            null
        ],
        [
            0.0,
            null
        ],
        [
            0.0,
            null
        ],
        [
            0.0,
            null
        ],
        [
            0.0,
            null
        ],
        [
            0.0,
            null
        ],
        [
            0.0,
            null
        ],
        [
            0.0,
            null
        ],
        [
            0.0,
            null
        ],
        [
            0.0,
            null
        ],
        [
            0.0,
            null
        ],
        [
            0.0,
            null
        ],
        [
            0.0,
            null
        ],
        [
            0.0,
            null
        ],
        [
            0.0,
            null
        ]
    ],
    "comp_est": [
        2.295082048122784e-05,
        0.05848410588726615,
        5.256347070656252,
        52.92194097245124,
        50.80750124237581,
        55.75350137935091,
        57.351076290671145,
        54.22150156679475,
        45.228548907055796,
        47.856092808152624,
        52.626741989927005,
        57.849630793320706,
        70.02698018909454,
        54.09904049774029,
        54.443104665199876,
        52.72675645256593,
        67.07612354676283,
        53.19485431536701,
        54.73672586908069,
        55.03154760800739,
        51.32210679866611,
        52.23440805995463,
        52.5329603377256,
        50.19500463509995,
        55.9181296903842,
        68.43879390536893,
        53.81720727593709,
        50.71402714269341
    ],
    "fit_time": 41005.47288894653,
    "init_guess": [
        5.848410588726615e-12,
        0.05848410588726615,
        4.0,
        55.0,
        55.0,
        55.0,
        55.0,
        55.0,
        55.0,
        55.0,
        55.0,
        55.0,
        55.0,
        55.0,
        55.0,
        55.0,
        55.0,
        55.0,
        55.0,
        55.0,
        55.0,
        55.0,
        55.0,
        55.0,
        55.0,
        55.0,
        55.0,
        55.0
    ],
    "model": "Competition Model",
    "model_params": [
        "C_0",
        "N_0",
        "kn",
        "rs"
    ],
    "model_species": [
        "C",
        "N"
    ],
    "obj_fun": 0.06651499821302184,
    "zone_cols": 5,
    "zone_coords": [
        7,
        13
    ],
    "zone_rows": 5
}