{
    "argv": 1184,
    "bounds": [
        [
            5.848410588726615e-12,
            0.005848410588726615
        ],
        [
            0.05848410588726615,
            0.1169682117745323
        ],
        [
            0.0,
            11.0
        ],
        [
            0.0,
            null
        ],
        [
            0.0,
            null
        ],
        [
            0.0,
            null
        ],
        [
            0.0,
            null
        ],
        [
            0.0,
            null
        ],
        [
            0.0,
            null
        ],
        [
            0.0,
            null
        ],
        [
            0.0,
            null
        ],
        [
            0.0,
            null
        ],
        [
            0.0,
            null
        ],
        [
            0.0,
            null
        ],
        [
            0.0,
            null
        ],
        [
            0.0,
            null
        ],
        [
            0.0,
            null
        ],
        [
            0.0,
            null
        ],
        [
            0.0,
            null
        ],
        [
            0.0,
            null
        ],
        [
            0.0,
            null
        ],
        [
            0.0,
            null
        ],
        [
            0.0,
            null
        ],
        [
            0.0,
            null
        ],
        [
            0.0,
            null
        ],
        [
            0.0,
            null
        ],
        [
            0.0,
            null
        ],
        [
            0.0,
            null
        ]
    ],
    "comp_est": [
        0.005848410584285391,
        0.05848410588726615,
        7.000000000000035,
        64.9999993777184,
        64.99999993624905,
        64.99999962859216,
        64.99999972166442,
        64.99999978237885,
        64.99999994002472,
        64.99999923764354,
        64.99999936178051,
        64.99999980260186,
        64.99999981771624,
        64.99999962096348,
        64.99999941895362,
        64.99999981609677,
        64.99999936069995,
        64.99999983255042,
        64.99999973471682,
        64.99999977326375,
        64.99999934290061,
        64.99999948788243,
        64.99999959128561,
        64.99999975080873,
        64.9999998121503,
        64.99999983005978,
        64.99999964749912,
        64.99999965275015
    ],
    "fit_time": 47325.81331658363,
    "init_guess": [
        0.005848410588726615,
        0.05848410588726615,
        7.0,
        65.0,
        65.0,
        65.0,
        65.0,
        65.0,
        65.0,
        65.0,
        65.0,
        65.0,
        65.0,
        65.0,
        65.0,
        65.0,
        65.0,
        65.0,
        65.0,
        65.0,
        65.0,
        65.0,
        65.0,
        65.0,
        65.0,
        65.0,
        65.0,
        65.0
    ],
    "model": "Competition Model",
    "model_params": [
        "C_0",
        "N_0",
        "kn",
        "rs"
    ],
    "model_species": [
        "C",
        "N"
    ],
    "obj_fun": 0.7162862631939175,
    "zone_cols": 5,
    "zone_coords": [
        7,
        13
    ],
    "zone_rows": 5
}