{
    "argv": 144,
    "bounds": [
        [
            6.437222058477453e-12,
            0.006437222058477453
        ],
        [
            0.06437222058477453,
            0.12874444116954906
        ],
        [
            0.0,
            11.0
        ],
        [
            0.0,
            null
        ],
        [
            0.0,
            null
        ],
        [
            0.0,
            null
        ],
        [
            0.0,
            null
        ],
        [
            0.0,
            null
        ],
        [
            0.0,
            null
        ],
        [
            0.0,
            null
        ],
        [
            0.0,
            null
        ],
        [
            0.0,
            null
        ],
        [
            0.0,
            null
        ],
        [
            0.0,
            null
        ],
        [
            0.0,
            null
        ],
        [
            0.0,
            null
        ],
        [
            0.0,
            null
        ],
        [
            0.0,
            null
        ],
        [
            0.0,
            null
        ],
        [
            0.0,
            null
        ],
        [
            0.0,
            null
        ],
        [
            0.0,
            null
        ],
        [
            0.0,
            null
        ],
        [
            0.0,
            null
        ],
        [
            0.0,
            null
        ],
        [
            0.0,
            null
        ],
        [
            0.0,
            null
        ],
        [
            0.0,
            null
        ]
    ],
    "comp_est": [
        7.346650438938786e-05,
        0.0733071825280367,
        1.0880631776155245,
        32.792968976568126,
        47.61938482215045,
        32.55759443020979,
        34.561524345596744,
        36.47846979654722,
        31.992003926695034,
        32.46715375701233,
        32.461848202476304,
        31.471888887218643,
        56.68632291213276,
        49.54346586644657,
        34.428009435560334,
        32.282215034303675,
        46.68079146553419,
        35.05240303226469,
        26.4340437098529,
        43.416497755018085,
        29.17604610526757,
        52.19428406545738,
        32.05525759552603,
        28.605338334163633,
        32.99412428677662,
        33.08257211355963,
        33.4848864854661,
        23.050004836924188
    ],
    "fit_time": 71544.0411977768,
    "init_guess": [
        6.437222058477453e-11,
        0.06437222058477453,
        1.0,
        35.0,
        35.0,
        35.0,
        35.0,
        35.0,
        35.0,
        35.0,
        35.0,
        35.0,
        35.0,
        35.0,
        35.0,
        35.0,
        35.0,
        35.0,
        35.0,
        35.0,
        35.0,
        35.0,
        35.0,
        35.0,
        35.0,
        35.0,
        35.0,
        35.0
    ],
    "model": "Competition Model",
    "model_params": [
        "C_0",
        "N_0",
        "kn",
        "rs"
    ],
    "model_species": [
        "C",
        "N"
    ],
    "obj_fun": 0.06231418011260397,
    "zone_cols": 5,
    "zone_coords": [
        9,
        15
    ],
    "zone_rows": 5
}