{
    "argv": 1104,
    "bounds": [
        [
            5.848410588726615e-12,
            0.005848410588726615
        ],
        [
            0.05848410588726615,
            0.1169682117745323
        ],
        [
            0.0,
            11.0
        ],
        [
            0.0,
            null
        ],
        [
            0.0,
            null
        ],
        [
            0.0,
            null
        ],
        [
            0.0,
            null
        ],
        [
            0.0,
            null
        ],
        [
            0.0,
            null
        ],
        [
            0.0,
            null
        ],
        [
            0.0,
            null
        ],
        [
            0.0,
            null
        ],
        [
            0.0,
            null
        ],
        [
            0.0,
            null
        ],
        [
            0.0,
            null
        ],
        [
            0.0,
            null
        ],
        [
            0.0,
            null
        ],
        [
            0.0,
            null
        ],
        [
            0.0,
            null
        ],
        [
            0.0,
            null
        ],
        [
            0.0,
            null
        ],
        [
            0.0,
            null
        ],
        [
            0.0,
            null
        ],
        [
            0.0,
            null
        ],
        [
            0.0,
            null
        ],
        [
            0.0,
            null
        ],
        [
            0.0,
            null
        ],
        [
            0.0,
            null
        ]
    ],
    "comp_est": [
        0.005848410588720124,
        0.05848410588726615,
        4.0,
        29.999999930069492,
        30.000000109846475,
        30.00000015538176,
        30.000000134715712,
        29.99999993958303,
        30.00000010987641,
        30.000000129992685,
        30.000000111288458,
        30.00000015555127,
        29.999999942608436,
        30.000000155309227,
        30.00000011102075,
        30.000000127139224,
        30.000000138621058,
        30.000000185186472,
        30.000000134745253,
        30.00000015556335,
        30.00000013853895,
        30.00000012254373,
        30.000000158403715,
        29.999999939401803,
        29.999999942583788,
        30.000000185321678,
        30.000000158317047,
        30.00000013336305
    ],
    "fit_time": 18090.153924942017,
    "init_guess": [
        0.005848410588726615,
        0.05848410588726615,
        4.0,
        30.0,
        30.0,
        30.0,
        30.0,
        30.0,
        30.0,
        30.0,
        30.0,
        30.0,
        30.0,
        30.0,
        30.0,
        30.0,
        30.0,
        30.0,
        30.0,
        30.0,
        30.0,
        30.0,
        30.0,
        30.0,
        30.0,
        30.0,
        30.0,
        30.0
    ],
    "model": "Competition Model",
    "model_params": [
        "C_0",
        "N_0",
        "kn",
        "rs"
    ],
    "model_species": [
        "C",
        "N"
    ],
    "obj_fun": 0.5433637886163094,
    "zone_cols": 5,
    "zone_coords": [
        7,
        13
    ],
    "zone_rows": 5
}