{
    "argv": 594,
    "bounds": [
        [
            5.848410588726615e-12,
            0.005848410588726615
        ],
        [
            0.05848410588726615,
            0.1169682117745323
        ],
        [
            0.0,
            11.0
        ],
        [
            0.0,
            null
        ],
        [
            0.0,
            null
        ],
        [
            0.0,
            null
        ],
        [
            0.0,
            null
        ],
        [
            0.0,
            null
        ],
        [
            0.0,
            null
        ],
        [
            0.0,
            null
        ],
        [
            0.0,
            null
        ],
        [
            0.0,
            null
        ],
        [
            0.0,
            null
        ],
        [
            0.0,
            null
        ],
        [
            0.0,
            null
        ],
        [
            0.0,
            null
        ],
        [
            0.0,
            null
        ],
        [
            0.0,
            null
        ],
        [
            0.0,
            null
        ],
        [
            0.0,
            null
        ],
        [
            0.0,
            null
        ],
        [
            0.0,
            null
        ],
        [
            0.0,
            null
        ],
        [
            0.0,
            null
        ],
        [
            0.0,
            null
        ],
        [
            0.0,
            null
        ],
        [
            0.0,
            null
        ],
        [
            0.0,
            null
        ]
    ],
    "comp_est": [
        1.2040484136213419e-06,
        0.05848410588726615,
        2.440519593509677,
        73.66792372632801,
        71.98729609625576,
        74.80164337467862,
        74.87719898247494,
        72.3863426004786,
        68.64021191150563,
        69.82384299604942,
        72.03150839109101,
        74.14583595463327,
        95.22464844702792,
        73.60188032578303,
        73.70879967646987,
        71.70693207292648,
        90.40772557121717,
        71.90759630409038,
        73.8462410034417,
        73.1326923142292,
        70.55090976254289,
        71.15282947773554,
        71.68017017027378,
        70.50607693757087,
        73.1725345664794,
        95.22345912655844,
        72.2410545597914,
        70.61778886723451
    ],
    "fit_time": 16609.76654958725,
    "init_guess": [
        5.8484105887266145e-08,
        0.05848410588726615,
        0.0,
        75.0,
        75.0,
        75.0,
        75.0,
        75.0,
        75.0,
        75.0,
        75.0,
        75.0,
        75.0,
        75.0,
        75.0,
        75.0,
        75.0,
        75.0,
        75.0,
        75.0,
        75.0,
        75.0,
        75.0,
        75.0,
        75.0,
        75.0,
        75.0,
        75.0
    ],
    "model": "Competition Model",
    "model_params": [
        "C_0",
        "N_0",
        "kn",
        "rs"
    ],
    "model_species": [
        "C",
        "N"
    ],
    "obj_fun": 0.12071402410328426,
    "zone_cols": 5,
    "zone_coords": [
        7,
        13
    ],
    "zone_rows": 5
}