{
    "argv": 1065,
    "bounds": [
        [
            5.848410588726615e-12,
            0.005848410588726615
        ],
        [
            0.05848410588726615,
            0.1169682117745323
        ],
        [
            0.0,
            11.0
        ],
        [
            0.0,
            null
        ],
        [
            0.0,
            null
        ],
        [
            0.0,
            null
        ],
        [
            0.0,
            null
        ],
        [
            0.0,
            null
        ],
        [
            0.0,
            null
        ],
        [
            0.0,
            null
        ],
        [
            0.0,
            null
        ],
        [
            0.0,
            null
        ],
        [
            0.0,
            null
        ],
        [
            0.0,
            null
        ],
        [
            0.0,
            null
        ],
        [
            0.0,
            null
        ],
        [
            0.0,
            null
        ],
        [
            0.0,
            null
        ],
        [
            0.0,
            null
        ],
        [
            0.0,
            null
        ],
        [
            0.0,
            null
        ],
        [
            0.0,
            null
        ],
        [
            0.0,
            null
        ],
        [
            0.0,
            null
        ],
        [
            0.0,
            null
        ],
        [
            0.0,
            null
        ],
        [
            0.0,
            null
        ],
        [
            0.0,
            null
        ]
    ],
    "comp_est": [
        0.0005848410588719986,
        0.05848410588726615,
        9.0,
        65.00000001466223,
        64.99999999270347,
        64.99999999108839,
        64.99999999345147,
        65.00000001577413,
        64.99999999270311,
        65.00000000174231,
        65.00000000051666,
        64.99999998419193,
        64.99999999335813,
        64.99999999108785,
        65.00000000051693,
        64.9999999898288,
        65.00000000049268,
        64.9999999945759,
        64.99999999345663,
        64.99999998419179,
        65.00000000048979,
        64.99999999202242,
        64.99999999302617,
        65.00000001578431,
        64.99999999335172,
        64.99999999457181,
        64.9999999930242,
        65.00000001916537
    ],
    "fit_time": 28886.1171708107,
    "init_guess": [
        0.0005848410588726615,
        0.05848410588726615,
        9.0,
        65.0,
        65.0,
        65.0,
        65.0,
        65.0,
        65.0,
        65.0,
        65.0,
        65.0,
        65.0,
        65.0,
        65.0,
        65.0,
        65.0,
        65.0,
        65.0,
        65.0,
        65.0,
        65.0,
        65.0,
        65.0,
        65.0,
        65.0,
        65.0,
        65.0
    ],
    "model": "Competition Model",
    "model_params": [
        "C_0",
        "N_0",
        "kn",
        "rs"
    ],
    "model_species": [
        "C",
        "N"
    ],
    "obj_fun": 0.5361001500259004,
    "zone_cols": 5,
    "zone_coords": [
        7,
        13
    ],
    "zone_rows": 5
}